colorir_terminal/__init__.py
colorir_terminal/app.py
colorir_terminal-0.1.2.dist-info/METADATA
colorir_terminal-0.1.2.dist-info/WHEEL
colorir_terminal-0.1.2.dist-info/RECORD
