Metadata-Version: 2.1
Name: colorir-terminal
Version: 0.1.2
Summary: 
Author: Jefferson L. Alionco
Author-email: Jeffersonalionco@gmail.com
Requires-Python: >=3.11,<4.0
Classifier: Programming Language :: Python :: 3
Classifier: Programming Language :: Python :: 3.11
Requires-Dist: color-terminal (>=1.0,<2.0)
